data_profiler/__init__.py
data_profiler/_version.py
data_profiler/util.py
data_profiler/checkpoint/__init__.py
data_profiler/checkpoint/actions.py
data_profiler/checkpoint/checkpoint.py
data_profiler/checkpoint/configurator.py
data_profiler/checkpoint/util.py
data_profiler/checkpoint/types/__init__.py
data_profiler/checkpoint/types/checkpoint_result.py
data_profiler/core/__init__.py
data_profiler/core/batch.py
data_profiler/core/batch_spec.py
data_profiler/core/data_context_key.py
data_profiler/core/evaluation_parameters.py
data_profiler/core/expectation_configuration.py
data_profiler/core/expectation_suite.py
data_profiler/core/expectation_validation_result.py
data_profiler/core/id_dict.py
data_profiler/core/metric.py
data_profiler/core/run_identifier.py
data_profiler/core/urn.py
data_profiler/core/util.py
data_profiler/core/usage_statistics/__init__.py
data_profiler/core/usage_statistics/schemas.py
data_profiler/core/usage_statistics/usage_statistics.py
data_profiler/core/usage_statistics/anonymizers/__init__.py
data_profiler/core/usage_statistics/anonymizers/action_anonymizer.py
data_profiler/core/usage_statistics/anonymizers/anonymizer.py
data_profiler/core/usage_statistics/anonymizers/batch_anonymizer.py
data_profiler/core/usage_statistics/anonymizers/batch_kwargs_anonymizer.py
data_profiler/core/usage_statistics/anonymizers/checkpoint_anonymizer.py
data_profiler/core/usage_statistics/anonymizers/data_connector_anonymizer.py
data_profiler/core/usage_statistics/anonymizers/data_docs_site_anonymizer.py
data_profiler/core/usage_statistics/anonymizers/datasource_anonymizer.py
data_profiler/core/usage_statistics/anonymizers/execution_engine_anonymizer.py
data_profiler/core/usage_statistics/anonymizers/expectation_suite_anonymizer.py
data_profiler/core/usage_statistics/anonymizers/site_builder_anonymizer.py
data_profiler/core/usage_statistics/anonymizers/store_anonymizer.py
data_profiler/core/usage_statistics/anonymizers/store_backend_anonymizer.py
openmetadata_data_profiler-0.2.0.dist-info/METADATA
openmetadata_data_profiler-0.2.0.dist-info/WHEEL
openmetadata_data_profiler-0.2.0.dist-info/entry_points.txt
openmetadata_data_profiler-0.2.0.dist-info/top_level.txt
openmetadata_data_profiler-0.2.0.dist-info/RECORD
